openfda_mcp_server/__init__.py
openfda_mcp_server/__main__.py
openfda_mcp_server/main.py
openfda_mcp_server/openfda_client.py
openfda_mcp_server-0.1.7.dist-info/METADATA
openfda_mcp_server-0.1.7.dist-info/WHEEL
openfda_mcp_server-0.1.7.dist-info/entry_points.txt
openfda_mcp_server-0.1.7.dist-info/RECORD
