Metadata-Version: 2.4
Name: openfda-mcp-server
Version: 0.1.7
Summary: A FastMCP server to expose drug safety analysis via OpenFDA API
Author-email: Praveen Bhati <praveenb@incubxperts.com>
License: MIT
Keywords: drug,llm,mcp,openfda
Requires-Python: >=3.8
Requires-Dist: mcp[cli]>=1.10.1
Requires-Dist: requests
Requires-Dist: uvicorn
